faker/__init__.py
faker/__main__.py
faker/cli.py
faker/config.py
faker/documentor.py
faker/exceptions.py
faker/factory.py
faker/generator.py
faker/proxy.py
faker/proxy.pyi
faker/py.typed
faker/typing.py
faker/contrib/__init__.py
faker/contrib/pytest/__init__.py
faker/contrib/pytest/plugin.py
faker/decode/__init__.py
faker/decode/codes.py
faker/providers/__init__.py
faker/providers/address/__init__.py
faker/providers/address/az_AZ/__init__.py
faker/providers/address/bn_BD/__init__.py
faker/providers/address/cs_CZ/__init__.py
faker/providers/address/da_DK/__init__.py
faker/providers/address/de/__init__.py
faker/providers/address/de_AT/__init__.py
faker/providers/address/de_CH/__init__.py
faker/providers/address/de_DE/__init__.py
faker/providers/address/el_GR/__init__.py
faker/providers/address/en/__init__.py
faker/providers/address/en_AU/__init__.py
faker/providers/address/en_BD/__init__.py
faker/providers/address/en_CA/__init__.py
faker/providers/address/en_GB/__init__.py
faker/providers/address/en_IE/__init__.py
faker/providers/address/en_IN/__init__.py
faker/providers/address/en_MS/__init__.py
faker/providers/address/en_NZ/__init__.py
faker/providers/address/en_PH/__init__.py
faker/providers/address/en_US/__init__.py
faker/providers/address/es/__init__.py
faker/providers/address/es_AR/__init__.py
faker/providers/address/es_CL/__init__.py
faker/providers/address/es_CO/__init__.py
faker/providers/address/es_ES/__init__.py
faker/providers/address/es_MX/__init__.py
faker/providers/address/fa_IR/__init__.py
faker/providers/address/fi_FI/__init__.py
faker/providers/address/fil_PH/__init__.py
faker/providers/address/fr_CA/__init__.py
faker/providers/address/fr_CH/__init__.py
faker/providers/address/fr_FR/__init__.py
faker/providers/address/he_IL/__init__.py
faker/providers/address/hi_IN/__init__.py
faker/providers/address/hr_HR/__init__.py
faker/providers/address/hu_HU/__init__.py
faker/providers/address/hy_AM/__init__.py
faker/providers/address/id_ID/__init__.py
faker-40.0.0.dist-info/licenses/LICENSE.txt
faker-40.0.0.dist-info/METADATA
faker-40.0.0.dist-info/WHEEL
faker-40.0.0.dist-info/entry_points.txt
faker-40.0.0.dist-info/top_level.txt
faker-40.0.0.dist-info/zip-safe
faker-40.0.0.dist-info/RECORD
