Metadata-Version: 2.4
Name: Faker
Version: 40.0.0
Summary: Faker is a Python package that generates fake data for you.
Home-page: https://github.com/joke2k/faker
Author: joke2k
Author-email: joke2k@gmail.com
License: MIT License
Project-URL: Bug Tracker, https://github.com/joke2k/faker/issues
Project-URL: Changes, https://github.com/joke2k/faker/blob/master/CHANGELOG.md
Project-URL: Documentation, http://faker.rtfd.org/
Project-URL: Source Code, https://github.com/joke2k/faker
Keywords: faker fixtures data test mock generator
Platform: any
Classifier: Development Status :: 5 - Production/Stable
Classifier: Environment :: Console
Classifier: Intended Audience :: Developers
Classifier: Programming Language :: Python :: 3.10
Classifier: Programming Language :: Python :: 3.11
Classifier: Programming Language :: Python :: 3.12
Classifier: Programming Language :: Python :: 3.13
Classifier: Programming Language :: Python :: 3.14
Classifier: Programming Language :: Python :: Implementation :: CPython
Classifier: Programming Language :: Python :: Implementation :: PyPy
Classifier: Topic :: Software Development :: Libraries :: Python Modules
Classifier: Topic :: Software Development :: Testing
Classifier: Topic :: Utilities
Classifier: License :: OSI Approved :: MIT License
Requires-Python: >=3.10
License-File: LICENSE.txt
Requires-Dist: tzdata
Dynamic: author
Dynamic: author-email
Dynamic: classifier
Dynamic: description
Dynamic: home-page
Dynamic: keywords
Dynamic: license
Dynamic: license-file
Dynamic: platform
Dynamic: project-url
Dynamic: requires-dist
Dynamic: requires-python
Dynamic: summary
